[
  {
    "type": "code",
    "named": true,
    "fields": {},
    "children": {
      "multiple": true,
      "required": false,
      "types": [
        {
          "type": "char",
          "named": true
        },
        {
          "type": "code",
          "named": true
        },
        {
          "type": "lifetime",
          "named": true
        },
        {
          "type": "string",
          "named": true
        }
      ]
    }
  },
  {
    "type": "document",
    "named": true,
    "root": true,
    "fields": {},
    "children": {
      "multiple": true,
      "required": false,
      "types": [
        {
          "type": "tag",
          "named": true
        },
        {
          "type": "text",
          "named": true
        }
      ]
    }
  },
  {
    "type": "tag",
    "named": true,
    "fields": {
      "close": {
        "multiple": false,
        "required": true,
        "types": [
          {
            "type": "tag_delimiter",
            "named": true
          }
        ]
      },
      "open": {
        "multiple": false,
        "required": true,
        "types": [
          {
            "type": "tag_open",
            "named": true
          }
        ]
      }
    },
    "children": {
      "multiple": false,
      "required": false,
      "types": [
        {
          "type": "code",
          "named": true
        }
      ]
    }
  },
  {
    "type": "tag_open",
    "named": true,
    "fields": {}
  },
  {
    "type": "char",
    "named": true
  },
  {
    "type": "lifetime",
    "named": true
  },
  {
    "type": "string",
    "named": true
  },
  {
    "type": "tag_delimiter",
    "named": false
  },
  {
    "type": "tag_delimiter",
    "named": true
  },
  {
    "type": "text",
    "named": true
  },
  {
    "type": "{",
    "named": false
  },
  {
    "type": "}",
    "named": false
  }
]